.gitignore
LICENSE
README.md
publish.sh
setup.py
speedian/__init__.py
speedian/annotations.py
speedian/command_handler.py
speedian/types.py
speedian.egg-info/PKG-INFO
speedian.egg-info/SOURCES.txt
speedian.egg-info/dependency_links.txt
speedian.egg-info/top_level.txt