Metadata-Version: 2.1
Name: speedian
Version: 1.1.4
Summary: A speedcord command handler
Home-page: UNKNOWN
Author: tag-epic
Author-email: tagepicuwu@gmail.com
License: UNKNOWN
Platform: UNKNOWN
License-File: LICENSE
